equate/__init__.py
equate/completion.py
equate/util.py
equate/examples/__init__.py
equate/examples/site_names.py
equate-0.0.11.dist-info/LICENSE
equate-0.0.11.dist-info/METADATA
equate-0.0.11.dist-info/WHEEL
equate-0.0.11.dist-info/top_level.txt
equate-0.0.11.dist-info/RECORD
