Metadata-Version: 2.1
Name: equate
Version: 0.0.11
Summary: "This is a package with tools for matching things. Dirty things like language, files in your file system, socks and whistles."
Home-page: https://github.com/thorwhalen/equate
Author: thorwhalen
License: mit
Keywords: matching,joining,connecting
Platform: any
License-File: LICENSE
Requires-Dist: py2store
Requires-Dist: pandas
Requires-Dist: numpy
